jupyter_environments/__init__.py
jupyter_environments/__main__.py
jupyter_environments/_version.py
jupyter_environments/application.py
jupyter_environments/serverapplication.py
jupyter_environments/handlers/__init__.py
jupyter_environments/handlers/base.py
jupyter_environments/handlers/config/__init__.py
jupyter_environments/handlers/config/handler.py
jupyter_environments/handlers/echo/__init__.py
jupyter_environments/handlers/echo/handler.py
jupyter_environments/handlers/environments/__init__.py
jupyter_environments/handlers/environments/handler.py
jupyter_environments/handlers/index/__init__.py
jupyter_environments/handlers/index/handler.py
jupyter_environments/handlers/ping/__init__.py
jupyter_environments/handlers/ping/handler.py
jupyter_environments/handlers/proxy/__init__.py
jupyter_environments/handlers/proxy/handler.py
jupyter_environments/handlers/relay/__init__.py
jupyter_environments/handlers/relay/handler.py
jupyter_environments/static/102.jupyter-environments.js
jupyter_environments/static/1020.jupyter-environments.js
jupyter_environments/static/1050.jupyter-environments.js
jupyter_environments/static/1109.jupyter-environments.js
jupyter_environments/static/1110.jupyter-environments.js
jupyter_environments/static/1146.jupyter-environments.js
jupyter_environments/static/1292.jupyter-environments.js
jupyter_environments/static/1450.jupyter-environments.js
jupyter_environments/static/1626.jupyter-environments.js
jupyter_environments/static/1629.jupyter-environments.js
jupyter_environments/static/1696.jupyter-environments.js
jupyter_environments/static/1810.jupyter-environments.js
jupyter_environments/static/1900.jupyter-environments.js
jupyter_environments/static/1919.jupyter-environments.js
jupyter_environments/static/1956.jupyter-environments.js
jupyter_environments/static/2.jupyter-environments.js
jupyter_environments/static/2003.jupyter-environments.js
jupyter_environments/static/2030.jupyter-environments.js
jupyter_environments-0.0.2.dist-info/METADATA
jupyter_environments-0.0.2.dist-info/WHEEL
jupyter_environments-0.0.2.dist-info/entry_points.txt
jupyter_environments-0.0.2.dist-info/licenses/LICENSE
jupyter_environments-0.0.2.dist-info/RECORD
